autotwin_autlib/automata_learner.py
autotwin_autlib/resources/learned_sha/.notempty
autotwin_autlib/resources/learned_sha/AUTO_TWIN_SKG_item-0
autotwin_autlib/resources/learned_sha/AUTO_TWIN_SKG_item-0.pdf
autotwin_autlib/resources/learned_sha/AUTO_TWIN_SKG_item-0.txt
autotwin_autlib/resources/learned_sha/AUTO_TWIN_SKG_item-0_source.txt
autotwin_autlib/resources/learned_sha/AUTO_TWIN_SKG_item-1
autotwin_autlib/resources/learned_sha/AUTO_TWIN_SKG_item-1.pdf
autotwin_autlib/resources/learned_sha/AUTO_TWIN_SKG_item-1.txt
autotwin_autlib/resources/learned_sha/AUTO_TWIN_SKG_item-10
autotwin_autlib/resources/learned_sha/AUTO_TWIN_SKG_item-10.pdf
autotwin_autlib/resources/learned_sha/AUTO_TWIN_SKG_item-10.txt
autotwin_autlib/resources/learned_sha/AUTO_TWIN_SKG_item-10_source.txt
autotwin_autlib/resources/learned_sha/AUTO_TWIN_SKG_item-11
autotwin_autlib/resources/learned_sha/AUTO_TWIN_SKG_item-11.pdf
autotwin_autlib/resources/learned_sha/AUTO_TWIN_SKG_item-11.txt
autotwin_autlib/resources/learned_sha/AUTO_TWIN_SKG_item-11_source.txt
autotwin_autlib/resources/learned_sha/AUTO_TWIN_SKG_item-1_source.txt
autotwin_autlib/resources/learned_sha/AUTO_TWIN_SKG_item-2
autotwin_autlib/resources/learned_sha/AUTO_TWIN_SKG_item-2.pdf
autotwin_autlib/resources/learned_sha/AUTO_TWIN_SKG_item-2.txt
autotwin_autlib/resources/learned_sha/AUTO_TWIN_SKG_item-2_source.txt
autotwin_autlib/resources/learned_sha/AUTO_TWIN_SKG_item-3
autotwin_autlib/resources/learned_sha/AUTO_TWIN_SKG_item-3.pdf
autotwin_autlib/resources/learned_sha/AUTO_TWIN_SKG_item-3.txt
autotwin_autlib/resources/learned_sha/AUTO_TWIN_SKG_item-3_source.txt
autotwin_autlib/resources/learned_sha/AUTO_TWIN_SKG_item-4
autotwin_autlib/resources/learned_sha/AUTO_TWIN_SKG_item-4.pdf
autotwin_autlib/resources/learned_sha/AUTO_TWIN_SKG_item-4.txt
autotwin_autlib/resources/learned_sha/AUTO_TWIN_SKG_item-4_source.txt
autotwin_autlib/resources/learned_sha/AUTO_TWIN_SKG_item-5
autotwin_autlib/resources/learned_sha/AUTO_TWIN_SKG_item-5.pdf
autotwin_autlib-0.1.6.dist-info/LICENSE
autotwin_autlib-0.1.6.dist-info/METADATA
autotwin_autlib-0.1.6.dist-info/WHEEL
autotwin_autlib-0.1.6.dist-info/RECORD
