Metadata-Version: 2.3
Name: autotwin_autlib
Version: 0.1.6
Summary: 
Author: livialestingi
Author-email: livia.lestingi@polimi.it
Requires-Python: >=3.10,<4.0
Classifier: Programming Language :: Python :: 3
Classifier: Programming Language :: Python :: 3.10
Classifier: Programming Language :: Python :: 3.11
Classifier: Programming Language :: Python :: 3.12
Classifier: Programming Language :: Python :: 3.13
Requires-Dist: graphviz (>=0.20.1,<0.21.0)
Requires-Dist: lsha (>=0.1.10,<0.2.0)
Requires-Dist: pygraphviz (>=1.12,<2.0)
Requires-Dist: sha2dt-semantic-mapper (>=0.1.9,<0.2.0)
Requires-Dist: skg_connector (>=0.1.16,<0.2.0)
